{
  "strava_id": 17234353979,
  "strava_name": "Morning Trail Run",
  "strava_url": "https://www.strava.com/activities/17234353979",
  "reps": [
    {
      "rep": 1,
      "up_alt_start": 18.8,
      "up_alt_end": 37.6,
      "up_elev": 18.8,
      "up_dur_s": 66,
      "up_dur": "1:06",
      "up_dist": 144.6,
      "up_hr": 144,
      "up_pace": "7:36",
      "dn_alt_start": 37.6,
      "dn_alt_end": 23.6,
      "dn_elev": 14.0,
      "dn_dur_s": 38,
      "dn_dur": "0:38",
      "dn_dist": 48.5,
      "dn_hr": 136,
      "dn_pace": "13:03",
      "full_dur_s": 104,
      "full_dur": "1:44",
      "full_dist": 193.1,
      "full_hr": 141,
      "si": 505,
      "pi": 571,
      "ei": 609
    },
    {
      "rep": 2,
      "up_alt_start": 23.6,
      "up_alt_end": 36.8,
      "up_elev": 13.2,
      "up_dur_s": 31,
      "up_dur": "0:31",
      "up_dist": 50.2,
      "up_hr": 130,
      "up_pace": "10:17",
      "dn_alt_start": 36.8,
      "dn_alt_end": 23.4,
      "dn_elev": 13.4,
      "dn_dur_s": 33,
      "dn_dur": "0:33",
      "dn_dist": 49.5,
      "dn_hr": 137,
      "dn_pace": "11:06",
      "full_dur_s": 64,
      "full_dur": "1:04",
      "full_dist": 99.7,
      "full_hr": 134,
      "si": 609,
      "pi": 640,
      "ei": 673
    },
    {
      "rep": 3,
      "up_alt_start": 23.4,
      "up_alt_end": 36.6,
      "up_elev": 13.2,
      "up_dur_s": 31,
      "up_dur": "0:31",
      "up_dist": 52.0,
      "up_hr": 133,
      "up_pace": "9:56",
      "dn_alt_start": 36.6,
      "dn_alt_end": 22.8,
      "dn_elev": 13.8,
      "dn_dur_s": 32,
      "dn_dur": "0:32",
      "dn_dist": 48.3,
      "dn_hr": 138,
      "dn_pace": "11:02",
      "full_dur_s": 63,
      "full_dur": "1:03",
      "full_dist": 100.3,
      "full_hr": 136,
      "si": 673,
      "pi": 704,
      "ei": 736
    },
    {
      "rep": 4,
      "up_alt_start": 22.8,
      "up_alt_end": 36.4,
      "up_elev": 13.6,
      "up_dur_s": 31,
      "up_dur": "0:31",
      "up_dist": 49.0,
      "up_hr": 134,
      "up_pace": "10:32",
      "dn_alt_start": 36.4,
      "dn_alt_end": 22.4,
      "dn_elev": 14.0,
      "dn_dur_s": 32,
      "dn_dur": "0:32",
      "dn_dist": 47.0,
      "dn_hr": 136,
      "dn_pace": "11:20",
      "full_dur_s": 63,
      "full_dur": "1:03",
      "full_dist": 96.0,
      "full_hr": 135,
      "si": 736,
      "pi": 767,
      "ei": 799
    },
    {
      "rep": 5,
      "up_alt_start": 22.4,
      "up_alt_end": 36.0,
      "up_elev": 13.6,
      "up_dur_s": 31,
      "up_dur": "0:31",
      "up_dist": 48.4,
      "up_hr": 132,
      "up_pace": "10:40",
      "dn_alt_start": 36.0,
      "dn_alt_end": 22.0,
      "dn_elev": 14.0,
      "dn_dur_s": 34,
      "dn_dur": "0:34",
      "dn_dist": 46.1,
      "dn_hr": 136,
      "dn_pace": "12:17",
      "full_dur_s": 65,
      "full_dur": "1:05",
      "full_dist": 94.5,
      "full_hr": 134,
      "si": 799,
      "pi": 830,
      "ei": 864
    },
    {
      "rep": 6,
      "up_alt_start": 22.0,
      "up_alt_end": 35.6,
      "up_elev": 13.6,
      "up_dur_s": 31,
      "up_dur": "0:31",
      "up_dist": 49.3,
      "up_hr": 135,
      "up_pace": "10:28",
      "dn_alt_start": 35.6,
      "dn_alt_end": 21.6,
      "dn_elev": 14.0,
      "dn_dur_s": 33,
      "dn_dur": "0:33",
      "dn_dist": 46.1,
      "dn_hr": 135,
      "dn_pace": "11:55",
      "full_dur_s": 64,
      "full_dur": "1:04",
      "full_dist": 95.4,
      "full_hr": 135,
      "si": 864,
      "pi": 895,
      "ei": 928
    },
    {
      "rep": 7,
      "up_alt_start": 21.6,
      "up_alt_end": 35.4,
      "up_elev": 13.8,
      "up_dur_s": 31,
      "up_dur": "0:31",
      "up_dist": 48.7,
      "up_hr": 135,
      "up_pace": "10:36",
      "dn_alt_start": 35.4,
      "dn_alt_end": 21.4,
      "dn_elev": 14.0,
      "dn_dur_s": 33,
      "dn_dur": "0:33",
      "dn_dist": 50.8,
      "dn_hr": 136,
      "dn_pace": "10:49",
      "full_dur_s": 64,
      "full_dur": "1:04",
      "full_dist": 99.5,
      "full_hr": 135,
      "si": 928,
      "pi": 959,
      "ei": 992
    },
    {
      "rep": 8,
      "up_alt_start": 21.4,
      "up_alt_end": 35.0,
      "up_elev": 13.6,
      "up_dur_s": 29,
      "up_dur": "0:29",
      "up_dist": 45.4,
      "up_hr": 137,
      "up_pace": "10:38",
      "dn_alt_start": 35.0,
      "dn_alt_end": 21.0,
      "dn_elev": 14.0,
      "dn_dur_s": 34,
      "dn_dur": "0:34",
      "dn_dist": 49.0,
      "dn_hr": 140,
      "dn_pace": "11:33",
      "full_dur_s": 63,
      "full_dur": "1:03",
      "full_dist": 94.4,
      "full_hr": 138,
      "si": 992,
      "pi": 1021,
      "ei": 1055
    },
    {
      "rep": 9,
      "up_alt_start": 21.0,
      "up_alt_end": 34.4,
      "up_elev": 13.4,
      "up_dur_s": 29,
      "up_dur": "0:29",
      "up_dist": 48.5,
      "up_hr": 137,
      "up_pace": "9:57",
      "dn_alt_start": 34.4,
      "dn_alt_end": 20.6,
      "dn_elev": 13.8,
      "dn_dur_s": 33,
      "dn_dur": "0:33",
      "dn_dist": 47.7,
      "dn_hr": 136,
      "dn_pace": "11:31",
      "full_dur_s": 62,
      "full_dur": "1:02",
      "full_dist": 96.2,
      "full_hr": 136,
      "si": 1055,
      "pi": 1084,
      "ei": 1117
    },
    {
      "rep": 10,
      "up_alt_start": 20.6,
      "up_alt_end": 34.2,
      "up_elev": 13.6,
      "up_dur_s": 30,
      "up_dur": "0:30",
      "up_dist": 49.2,
      "up_hr": 136,
      "up_pace": "10:09",
      "dn_alt_start": 34.2,
      "dn_alt_end": 20.2,
      "dn_elev": 14.0,
      "dn_dur_s": 34,
      "dn_dur": "0:34",
      "dn_dist": 46.5,
      "dn_hr": 140,
      "dn_pace": "12:11",
      "full_dur_s": 64,
      "full_dur": "1:04",
      "full_dist": 95.7,
      "full_hr": 138,
      "si": 1117,
      "pi": 1147,
      "ei": 1181
    },
    {
      "rep": 11,
      "up_alt_start": 20.2,
      "up_alt_end": 33.8,
      "up_elev": 13.6,
      "up_dur_s": 30,
      "up_dur": "0:30",
      "up_dist": 47.9,
      "up_hr": 138,
      "up_pace": "10:26",
      "dn_alt_start": 33.8,
      "dn_alt_end": 20.0,
      "dn_elev": 13.8,
      "dn_dur_s": 32,
      "dn_dur": "0:32",
      "dn_dist": 49.6,
      "dn_hr": 141,
      "dn_pace": "10:45",
      "full_dur_s": 62,
      "full_dur": "1:02",
      "full_dist": 97.5,
      "full_hr": 140,
      "si": 1181,
      "pi": 1211,
      "ei": 1243
    },
    {
      "rep": 12,
      "up_alt_start": 20.0,
      "up_alt_end": 33.6,
      "up_elev": 13.6,
      "up_dur_s": 30,
      "up_dur": "0:30",
      "up_dist": 49.0,
      "up_hr": 141,
      "up_pace": "10:12",
      "dn_alt_start": 33.6,
      "dn_alt_end": 19.6,
      "dn_elev": 14.0,
      "dn_dur_s": 32,
      "dn_dur": "0:32",
      "dn_dist": 46.9,
      "dn_hr": 143,
      "dn_pace": "11:22",
      "full_dur_s": 62,
      "full_dur": "1:02",
      "full_dist": 95.9,
      "full_hr": 142,
      "si": 1243,
      "pi": 1273,
      "ei": 1305
    },
    {
      "rep": 13,
      "up_alt_start": 19.6,
      "up_alt_end": 33.2,
      "up_elev": 13.6,
      "up_dur_s": 29,
      "up_dur": "0:29",
      "up_dist": 46.3,
      "up_hr": 139,
      "up_pace": "10:26",
      "dn_alt_start": 33.2,
      "dn_alt_end": 19.4,
      "dn_elev": 13.8,
      "dn_dur_s": 34,
      "dn_dur": "0:34",
      "dn_dist": 47.6,
      "dn_hr": 143,
      "dn_pace": "11:54",
      "full_dur_s": 63,
      "full_dur": "1:03",
      "full_dist": 93.9,
      "full_hr": 141,
      "si": 1305,
      "pi": 1334,
      "ei": 1368
    },
    {
      "rep": 14,
      "up_alt_start": 19.4,
      "up_alt_end": 33.0,
      "up_elev": 13.6,
      "up_dur_s": 29,
      "up_dur": "0:29",
      "up_dist": 50.0,
      "up_hr": 139,
      "up_pace": "9:40",
      "dn_alt_start": 33.0,
      "dn_alt_end": 19.2,
      "dn_elev": 13.8,
      "dn_dur_s": 33,
      "dn_dur": "0:33",
      "dn_dist": 46.0,
      "dn_hr": 146,
      "dn_pace": "11:57",
      "full_dur_s": 62,
      "full_dur": "1:02",
      "full_dist": 96.0,
      "full_hr": 143,
      "si": 1368,
      "pi": 1397,
      "ei": 1430
    },
    {
      "rep": 15,
      "up_alt_start": 19.2,
      "up_alt_end": 32.6,
      "up_elev": 13.4,
      "up_dur_s": 29,
      "up_dur": "0:29",
      "up_dist": 48.5,
      "up_hr": 142,
      "up_pace": "9:57",
      "dn_alt_start": 32.6,
      "dn_alt_end": 18.8,
      "dn_elev": 13.8,
      "dn_dur_s": 34,
      "dn_dur": "0:34",
      "dn_dist": 48.5,
      "dn_hr": 145,
      "dn_pace": "11:41",
      "full_dur_s": 63,
      "full_dur": "1:03",
      "full_dist": 97.0,
      "full_hr": 144,
      "si": 1430,
      "pi": 1459,
      "ei": 1493
    },
    {
      "rep": 16,
      "up_alt_start": 18.8,
      "up_alt_end": 32.2,
      "up_elev": 13.4,
      "up_dur_s": 29,
      "up_dur": "0:29",
      "up_dist": 46.7,
      "up_hr": 140,
      "up_pace": "10:20",
      "dn_alt_start": 32.2,
      "dn_alt_end": 18.4,
      "dn_elev": 13.8,
      "dn_dur_s": 34,
      "dn_dur": "0:34",
      "dn_dist": 51.6,
      "dn_hr": 146,
      "dn_pace": "10:58",
      "full_dur_s": 63,
      "full_dur": "1:03",
      "full_dist": 98.3,
      "full_hr": 143,
      "si": 1493,
      "pi": 1522,
      "ei": 1556
    },
    {
      "rep": 17,
      "up_alt_start": 18.4,
      "up_alt_end": 32.0,
      "up_elev": 13.6,
      "up_dur_s": 30,
      "up_dur": "0:30",
      "up_dist": 47.9,
      "up_hr": 142,
      "up_pace": "10:26",
      "dn_alt_start": 32.0,
      "dn_alt_end": 18.2,
      "dn_elev": 13.8,
      "dn_dur_s": 33,
      "dn_dur": "0:33",
      "dn_dist": 48.0,
      "dn_hr": 143,
      "dn_pace": "11:27",
      "full_dur_s": 63,
      "full_dur": "1:03",
      "full_dist": 95.9,
      "full_hr": 142,
      "si": 1556,
      "pi": 1586,
      "ei": 1619
    },
    {
      "rep": 18,
      "up_alt_start": 18.2,
      "up_alt_end": 32.0,
      "up_elev": 13.8,
      "up_dur_s": 32,
      "up_dur": "0:32",
      "up_dist": 50.3,
      "up_hr": 141,
      "up_pace": "10:36",
      "dn_alt_start": 32.0,
      "dn_alt_end": 18.0,
      "dn_elev": 14.0,
      "dn_dur_s": 33,
      "dn_dur": "0:33",
      "dn_dist": 49.3,
      "dn_hr": 142,
      "dn_pace": "11:09",
      "full_dur_s": 65,
      "full_dur": "1:05",
      "full_dist": 99.6,
      "full_hr": 141,
      "si": 1619,
      "pi": 1651,
      "ei": 1684
    },
    {
      "rep": 19,
      "up_alt_start": 18.0,
      "up_alt_end": 31.6,
      "up_elev": 13.6,
      "up_dur_s": 30,
      "up_dur": "0:30",
      "up_dist": 48.2,
      "up_hr": 142,
      "up_pace": "10:22",
      "dn_alt_start": 31.6,
      "dn_alt_end": 17.6,
      "dn_elev": 14.0,
      "dn_dur_s": 34,
      "dn_dur": "0:34",
      "dn_dist": 52.3,
      "dn_hr": 143,
      "dn_pace": "10:50",
      "full_dur_s": 64,
      "full_dur": "1:04",
      "full_dist": 100.5,
      "full_hr": 142,
      "si": 1684,
      "pi": 1714,
      "ei": 1748
    },
    {
      "rep": 20,
      "up_alt_start": 17.6,
      "up_alt_end": 31.2,
      "up_elev": 13.6,
      "up_dur_s": 29,
      "up_dur": "0:29",
      "up_dist": 47.4,
      "up_hr": 142,
      "up_pace": "10:11",
      "dn_alt_start": 31.2,
      "dn_alt_end": 17.4,
      "dn_elev": 13.8,
      "dn_dur_s": 33,
      "dn_dur": "0:33",
      "dn_dist": 50.2,
      "dn_hr": 145,
      "dn_pace": "10:57",
      "full_dur_s": 62,
      "full_dur": "1:02",
      "full_dist": 97.6,
      "full_hr": 144,
      "si": 1748,
      "pi": 1777,
      "ei": 1810
    },
    {
      "rep": 21,
      "up_alt_start": 17.4,
      "up_alt_end": 30.8,
      "up_elev": 13.4,
      "up_dur_s": 30,
      "up_dur": "0:30",
      "up_dist": 47.9,
      "up_hr": 140,
      "up_pace": "10:26",
      "dn_alt_start": 30.8,
      "dn_alt_end": 17.2,
      "dn_elev": 13.6,
      "dn_dur_s": 33,
      "dn_dur": "0:33",
      "dn_dist": 48.4,
      "dn_hr": 141,
      "dn_pace": "11:21",
      "full_dur_s": 63,
      "full_dur": "1:03",
      "full_dist": 96.3,
      "full_hr": 141,
      "si": 1810,
      "pi": 1840,
      "ei": 1873
    },
    {
      "rep": 22,
      "up_alt_start": 17.2,
      "up_alt_end": 30.6,
      "up_elev": 13.4,
      "up_dur_s": 30,
      "up_dur": "0:30",
      "up_dist": 49.8,
      "up_hr": 143,
      "up_pace": "10:02",
      "dn_alt_start": 30.6,
      "dn_alt_end": 16.6,
      "dn_elev": 14.0,
      "dn_dur_s": 34,
      "dn_dur": "0:34",
      "dn_dist": 49.2,
      "dn_hr": 145,
      "dn_pace": "11:31",
      "full_dur_s": 64,
      "full_dur": "1:04",
      "full_dist": 99.0,
      "full_hr": 144,
      "si": 1873,
      "pi": 1903,
      "ei": 1937
    },
    {
      "rep": 23,
      "up_alt_start": 16.6,
      "up_alt_end": 30.2,
      "up_elev": 13.6,
      "up_dur_s": 29,
      "up_dur": "0:29",
      "up_dist": 47.7,
      "up_hr": 143,
      "up_pace": "10:07",
      "dn_alt_start": 30.2,
      "dn_alt_end": 16.4,
      "dn_elev": 13.8,
      "dn_dur_s": 34,
      "dn_dur": "0:34",
      "dn_dist": 48.8,
      "dn_hr": 143,
      "dn_pace": "11:36",
      "full_dur_s": 63,
      "full_dur": "1:03",
      "full_dist": 96.5,
      "full_hr": 143,
      "si": 1937,
      "pi": 1966,
      "ei": 2000
    },
    {
      "rep": 24,
      "up_alt_start": 16.4,
      "up_alt_end": 30.2,
      "up_elev": 13.8,
      "up_dur_s": 36,
      "up_dur": "0:36",
      "up_dist": 46.4,
      "up_hr": 137,
      "up_pace": "12:55",
      "dn_alt_start": 30.2,
      "dn_alt_end": 16.2,
      "dn_elev": 14.0,
      "dn_dur_s": 34,
      "dn_dur": "0:34",
      "dn_dist": 47.2,
      "dn_hr": 138,
      "dn_pace": "12:00",
      "full_dur_s": 70,
      "full_dur": "1:10",
      "full_dist": 93.6,
      "full_hr": 137,
      "si": 2000,
      "pi": 2036,
      "ei": 2070
    },
    {
      "rep": 25,
      "up_alt_start": 16.2,
      "up_alt_end": 29.8,
      "up_elev": 13.6,
      "up_dur_s": 31,
      "up_dur": "0:31",
      "up_dist": 48.7,
      "up_hr": 139,
      "up_pace": "10:36",
      "dn_alt_start": 29.8,
      "dn_alt_end": 16.0,
      "dn_elev": 13.8,
      "dn_dur_s": 33,
      "dn_dur": "0:33",
      "dn_dist": 51.2,
      "dn_hr": 144,
      "dn_pace": "10:44",
      "full_dur_s": 64,
      "full_dur": "1:04",
      "full_dist": 99.9,
      "full_hr": 141,
      "si": 2070,
      "pi": 2101,
      "ei": 2134
    },
    {
      "rep": 26,
      "up_alt_start": 16.0,
      "up_alt_end": 29.6,
      "up_elev": 13.6,
      "up_dur_s": 30,
      "up_dur": "0:30",
      "up_dist": 49.4,
      "up_hr": 140,
      "up_pace": "10:07",
      "dn_alt_start": 29.6,
      "dn_alt_end": 15.8,
      "dn_elev": 13.8,
      "dn_dur_s": 33,
      "dn_dur": "0:33",
      "dn_dist": 48.3,
      "dn_hr": 146,
      "dn_pace": "11:23",
      "full_dur_s": 63,
      "full_dur": "1:03",
      "full_dist": 97.7,
      "full_hr": 143,
      "si": 2134,
      "pi": 2164,
      "ei": 2197
    },
    {
      "rep": 27,
      "up_alt_start": 15.8,
      "up_alt_end": 29.2,
      "up_elev": 13.4,
      "up_dur_s": 28,
      "up_dur": "0:28",
      "up_dist": 50.0,
      "up_hr": 144,
      "up_pace": "9:20",
      "dn_alt_start": 29.2,
      "dn_alt_end": 15.4,
      "dn_elev": 13.8,
      "dn_dur_s": 35,
      "dn_dur": "0:35",
      "dn_dist": 48.5,
      "dn_hr": 149,
      "dn_pace": "12:01",
      "full_dur_s": 63,
      "full_dur": "1:03",
      "full_dist": 98.5,
      "full_hr": 147,
      "si": 2197,
      "pi": 2225,
      "ei": 2260
    },
    {
      "rep": 28,
      "up_alt_start": 15.4,
      "up_alt_end": 28.8,
      "up_elev": 13.4,
      "up_dur_s": 28,
      "up_dur": "0:28",
      "up_dist": 46.1,
      "up_hr": 142,
      "up_pace": "10:07",
      "dn_alt_start": 28.8,
      "dn_alt_end": 15.2,
      "dn_elev": 13.6,
      "dn_dur_s": 52,
      "dn_dur": "0:52",
      "dn_dist": 44.5,
      "dn_hr": 134,
      "dn_pace": "19:28",
      "full_dur_s": 80,
      "full_dur": "1:20",
      "full_dist": 90.6,
      "full_hr": 138,
      "si": 2260,
      "pi": 2288,
      "ei": 2323
    },
    {
      "rep": 29,
      "up_alt_start": 15.2,
      "up_alt_end": 28.8,
      "up_elev": 13.6,
      "up_dur_s": 30,
      "up_dur": "0:30",
      "up_dist": 46.6,
      "up_hr": 133,
      "up_pace": "10:43",
      "dn_alt_start": 28.8,
      "dn_alt_end": 15.0,
      "dn_elev": 13.8,
      "dn_dur_s": 33,
      "dn_dur": "0:33",
      "dn_dist": 49.3,
      "dn_hr": 142,
      "dn_pace": "11:09",
      "full_dur_s": 63,
      "full_dur": "1:03",
      "full_dist": 95.9,
      "full_hr": 138,
      "si": 2323,
      "pi": 2353,
      "ei": 2386
    },
    {
      "rep": 30,
      "up_alt_start": 15.0,
      "up_alt_end": 28.6,
      "up_elev": 13.6,
      "up_dur_s": 30,
      "up_dur": "0:30",
      "up_dist": 47.6,
      "up_hr": 140,
      "up_pace": "10:30",
      "dn_alt_start": 28.6,
      "dn_alt_end": 15.0,
      "dn_elev": 13.6,
      "dn_dur_s": 33,
      "dn_dur": "0:33",
      "dn_dist": 49.5,
      "dn_hr": 146,
      "dn_pace": "11:06",
      "full_dur_s": 63,
      "full_dur": "1:03",
      "full_dist": 97.1,
      "full_hr": 143,
      "si": 2386,
      "pi": 2416,
      "ei": 2449
    },
    {
      "rep": 31,
      "up_alt_start": 15.0,
      "up_alt_end": 28.8,
      "up_elev": 13.8,
      "up_dur_s": 28,
      "up_dur": "0:28",
      "up_dist": 45.5,
      "up_hr": 143,
      "up_pace": "10:15",
      "dn_alt_start": 28.8,
      "dn_alt_end": 15.0,
      "dn_elev": 13.8,
      "dn_dur_s": 32,
      "dn_dur": "0:32",
      "dn_dist": 48.0,
      "dn_hr": 148,
      "dn_pace": "11:06",
      "full_dur_s": 60,
      "full_dur": "1:00",
      "full_dist": 93.5,
      "full_hr": 145,
      "si": 2449,
      "pi": 2477,
      "ei": 2509
    },
    {
      "rep": 32,
      "up_alt_start": 15.0,
      "up_alt_end": 28.4,
      "up_elev": 13.4,
      "up_dur_s": 31,
      "up_dur": "0:31",
      "up_dist": 51.4,
      "up_hr": 145,
      "up_pace": "10:03",
      "dn_alt_start": 28.4,
      "dn_alt_end": 14.8,
      "dn_elev": 13.6,
      "dn_dur_s": 32,
      "dn_dur": "0:32",
      "dn_dist": 45.2,
      "dn_hr": 148,
      "dn_pace": "11:47",
      "full_dur_s": 63,
      "full_dur": "1:03",
      "full_dist": 96.6,
      "full_hr": 147,
      "si": 2509,
      "pi": 2540,
      "ei": 2572
    },
    {
      "rep": 33,
      "up_alt_start": 14.8,
      "up_alt_end": 28.6,
      "up_elev": 13.8,
      "up_dur_s": 30,
      "up_dur": "0:30",
      "up_dist": 48.7,
      "up_hr": 146,
      "up_pace": "10:16",
      "dn_alt_start": 28.6,
      "dn_alt_end": 14.4,
      "dn_elev": 14.2,
      "dn_dur_s": 32,
      "dn_dur": "0:32",
      "dn_dist": 47.3,
      "dn_hr": 150,
      "dn_pace": "11:16",
      "full_dur_s": 62,
      "full_dur": "1:02",
      "full_dist": 96.0,
      "full_hr": 148,
      "si": 2572,
      "pi": 2602,
      "ei": 2634
    },
    {
      "rep": 34,
      "up_alt_start": 14.4,
      "up_alt_end": 28.2,
      "up_elev": 13.8,
      "up_dur_s": 29,
      "up_dur": "0:29",
      "up_dist": 48.3,
      "up_hr": 145,
      "up_pace": "10:00",
      "dn_alt_start": 28.2,
      "dn_alt_end": 14.0,
      "dn_elev": 14.2,
      "dn_dur_s": 38,
      "dn_dur": "0:38",
      "dn_dist": 65.4,
      "dn_hr": 147,
      "dn_pace": "9:41",
      "full_dur_s": 67,
      "full_dur": "1:07",
      "full_dist": 113.7,
      "full_hr": 146,
      "si": 2634,
      "pi": 2663,
      "ei": 2701
    }
  ],
  "chart": [
    {
      "t": 0.0,
      "a": 19.8
    },
    {
      "t": 5.0,
      "a": 19.6
    },
    {
      "t": 10.0,
      "a": 19.8
    },
    {
      "t": 15.0,
      "a": 19.4
    },
    {
      "t": 20.0,
      "a": 19.6
    },
    {
      "t": 25.0,
      "a": 19.8
    },
    {
      "t": 30.0,
      "a": 19.6
    },
    {
      "t": 35.0,
      "a": 20.0
    },
    {
      "t": 40.0,
      "a": 19.4
    },
    {
      "t": 45.0,
      "a": 19.2
    },
    {
      "t": 50.0,
      "a": 19.4
    },
    {
      "t": 55.0,
      "a": 19.2
    },
    {
      "t": 60.0,
      "a": 19.4
    },
    {
      "t": 65.0,
      "a": 20.0
    },
    {
      "t": 70.0,
      "a": 20.6
    },
    {
      "t": 75.0,
      "a": 21.2
    },
    {
      "t": 80.0,
      "a": 21.2
    },
    {
      "t": 85.0,
      "a": 21.2
    },
    {
      "t": 90.0,
      "a": 21.4
    },
    {
      "t": 95.0,
      "a": 21.6
    },
    {
      "t": 100.0,
      "a": 21.2
    },
    {
      "t": 105.0,
      "a": 21.0
    },
    {
      "t": 110.0,
      "a": 20.8
    },
    {
      "t": 115.0,
      "a": 21.2
    },
    {
      "t": 120.0,
      "a": 20.8
    },
    {
      "t": 125.0,
      "a": 20.8
    },
    {
      "t": 130.0,
      "a": 20.4
    },
    {
      "t": 135.0,
      "a": 20.4
    },
    {
      "t": 140.0,
      "a": 20.0
    },
    {
      "t": 145.0,
      "a": 20.0
    },
    {
      "t": 150.0,
      "a": 19.6
    },
    {
      "t": 155.0,
      "a": 19.4
    },
    {
      "t": 160.0,
      "a": 19.4
    },
    {
      "t": 165.0,
      "a": 19.4
    },
    {
      "t": 170.0,
      "a": 19.6
    },
    {
      "t": 175.0,
      "a": 20.2
    },
    {
      "t": 180.0,
      "a": 19.4
    },
    {
      "t": 185.0,
      "a": 19.2
    },
    {
      "t": 190.0,
      "a": 19.0
    },
    {
      "t": 195.0,
      "a": 18.6
    },
    {
      "t": 200.0,
      "a": 18.4
    },
    {
      "t": 205.0,
      "a": 18.4
    },
    {
      "t": 210.0,
      "a": 18.0
    },
    {
      "t": 215.0,
      "a": 17.8
    },
    {
      "t": 220.0,
      "a": 17.2
    },
    {
      "t": 225.0,
      "a": 17.2
    },
    {
      "t": 230.0,
      "a": 17.0
    },
    {
      "t": 235.0,
      "a": 17.0
    },
    {
      "t": 240.0,
      "a": 17.0
    },
    {
      "t": 245.0,
      "a": 16.6
    },
    {
      "t": 250.0,
      "a": 16.6
    },
    {
      "t": 255.0,
      "a": 16.2
    },
    {
      "t": 260.0,
      "a": 16.0
    },
    {
      "t": 265.0,
      "a": 16.0
    },
    {
      "t": 270.0,
      "a": 16.2
    },
    {
      "t": 275.0,
      "a": 16.2
    },
    {
      "t": 280.0,
      "a": 16.0
    },
    {
      "t": 285.0,
      "a": 16.0
    },
    {
      "t": 290.0,
      "a": 15.8
    },
    {
      "t": 295.0,
      "a": 15.8
    },
    {
      "t": 300.0,
      "a": 15.6
    },
    {
      "t": 305.0,
      "a": 15.8
    },
    {
      "t": 310.0,
      "a": 15.8
    },
    {
      "t": 315.0,
      "a": 15.8
    },
    {
      "t": 320.0,
      "a": 15.8
    },
    {
      "t": 325.0,
      "a": 15.8
    },
    {
      "t": 330.0,
      "a": 15.6
    },
    {
      "t": 335.0,
      "a": 15.6
    },
    {
      "t": 340.0,
      "a": 15.4
    },
    {
      "t": 345.0,
      "a": 15.8
    },
    {
      "t": 350.0,
      "a": 15.6
    },
    {
      "t": 355.0,
      "a": 15.6
    },
    {
      "t": 360.0,
      "a": 15.6
    },
    {
      "t": 365.0,
      "a": 15.6
    },
    {
      "t": 370.0,
      "a": 15.4
    },
    {
      "t": 375.0,
      "a": 15.4
    },
    {
      "t": 380.0,
      "a": 15.4
    },
    {
      "t": 385.0,
      "a": 15.4
    },
    {
      "t": 390.0,
      "a": 15.4
    },
    {
      "t": 395.0,
      "a": 15.4
    },
    {
      "t": 400.0,
      "a": 15.4
    },
    {
      "t": 405.0,
      "a": 15.4
    },
    {
      "t": 410.0,
      "a": 15.4
    },
    {
      "t": 415.0,
      "a": 15.6
    },
    {
      "t": 420.0,
      "a": 15.6
    },
    {
      "t": 425.0,
      "a": 15.4
    },
    {
      "t": 430.0,
      "a": 15.4
    },
    {
      "t": 435.0,
      "a": 15.4
    },
    {
      "t": 440.0,
      "a": 15.2
    },
    {
      "t": 445.0,
      "a": 15.0
    },
    {
      "t": 450.0,
      "a": 15.4
    },
    {
      "t": 455.0,
      "a": 15.8
    },
    {
      "t": 460.0,
      "a": 16.0
    },
    {
      "t": 465.0,
      "a": 16.0
    },
    {
      "t": 470.0,
      "a": 16.0
    },
    {
      "t": 475.0,
      "a": 16.2
    },
    {
      "t": 480.0,
      "a": 16.6
    },
    {
      "t": 485.0,
      "a": 16.8
    },
    {
      "t": 490.0,
      "a": 17.2
    },
    {
      "t": 495.0,
      "a": 17.6
    },
    {
      "t": 500.0,
      "a": 17.8
    },
    {
      "t": 505.0,
      "a": 18.8
    },
    {
      "t": 510.0,
      "a": 19.8
    },
    {
      "t": 515.0,
      "a": 21.0
    },
    {
      "t": 520.0,
      "a": 22.2
    },
    {
      "t": 525.0,
      "a": 22.8
    },
    {
      "t": 530.0,
      "a": 23.4
    },
    {
      "t": 535.0,
      "a": 24.0
    },
    {
      "t": 540.0,
      "a": 24.2
    },
    {
      "t": 545.0,
      "a": 26.4
    },
    {
      "t": 550.0,
      "a": 29.8
    },
    {
      "t": 555.0,
      "a": 31.8
    },
    {
      "t": 560.0,
      "a": 34.0
    },
    {
      "t": 565.0,
      "a": 35.8
    },
    {
      "t": 570.0,
      "a": 37.4
    },
    {
      "t": 575.0,
      "a": 37.0
    },
    {
      "t": 580.0,
      "a": 36.0
    },
    {
      "t": 585.0,
      "a": 34.2
    },
    {
      "t": 590.0,
      "a": 32.0
    },
    {
      "t": 595.0,
      "a": 29.6
    },
    {
      "t": 600.0,
      "a": 27.6
    },
    {
      "t": 605.0,
      "a": 25.2
    },
    {
      "t": 610.0,
      "a": 23.6
    },
    {
      "t": 615.0,
      "a": 25.6
    },
    {
      "t": 620.0,
      "a": 28.8
    },
    {
      "t": 625.0,
      "a": 31.4
    },
    {
      "t": 630.0,
      "a": 33.4
    },
    {
      "t": 635.0,
      "a": 35.6
    },
    {
      "t": 640.0,
      "a": 36.8
    },
    {
      "t": 645.0,
      "a": 36.4
    },
    {
      "t": 650.0,
      "a": 34.2
    },
    {
      "t": 655.0,
      "a": 31.8
    },
    {
      "t": 660.0,
      "a": 29.4
    },
    {
      "t": 665.0,
      "a": 27.0
    },
    {
      "t": 670.0,
      "a": 24.6
    },
    {
      "t": 675.0,
      "a": 23.4
    },
    {
      "t": 680.0,
      "a": 26.0
    },
    {
      "t": 685.0,
      "a": 29.4
    },
    {
      "t": 690.0,
      "a": 31.8
    },
    {
      "t": 695.0,
      "a": 34.0
    },
    {
      "t": 700.0,
      "a": 35.6
    },
    {
      "t": 705.0,
      "a": 36.6
    },
    {
      "t": 710.0,
      "a": 35.4
    },
    {
      "t": 715.0,
      "a": 33.2
    },
    {
      "t": 720.0,
      "a": 30.6
    },
    {
      "t": 725.0,
      "a": 28.2
    },
    {
      "t": 730.0,
      "a": 25.6
    },
    {
      "t": 735.0,
      "a": 23.0
    },
    {
      "t": 740.0,
      "a": 23.8
    },
    {
      "t": 745.0,
      "a": 27.0
    },
    {
      "t": 750.0,
      "a": 30.4
    },
    {
      "t": 755.0,
      "a": 32.4
    },
    {
      "t": 760.0,
      "a": 34.6
    },
    {
      "t": 765.0,
      "a": 36.2
    },
    {
      "t": 770.0,
      "a": 36.0
    },
    {
      "t": 775.0,
      "a": 33.8
    },
    {
      "t": 780.0,
      "a": 31.4
    },
    {
      "t": 785.0,
      "a": 28.8
    },
    {
      "t": 790.0,
      "a": 26.4
    },
    {
      "t": 795.0,
      "a": 23.8
    },
    {
      "t": 800.0,
      "a": 22.4
    },
    {
      "t": 805.0,
      "a": 24.6
    },
    {
      "t": 810.0,
      "a": 28.0
    },
    {
      "t": 815.0,
      "a": 30.4
    },
    {
      "t": 820.0,
      "a": 32.6
    },
    {
      "t": 825.0,
      "a": 34.4
    },
    {
      "t": 830.0,
      "a": 36.0
    },
    {
      "t": 835.0,
      "a": 35.2
    },
    {
      "t": 840.0,
      "a": 33.4
    },
    {
      "t": 845.0,
      "a": 31.0
    },
    {
      "t": 850.0,
      "a": 28.4
    },
    {
      "t": 855.0,
      "a": 26.0
    },
    {
      "t": 860.0,
      "a": 23.6
    },
    {
      "t": 865.0,
      "a": 22.0
    },
    {
      "t": 870.0,
      "a": 24.2
    },
    {
      "t": 875.0,
      "a": 27.8
    },
    {
      "t": 880.0,
      "a": 30.4
    },
    {
      "t": 885.0,
      "a": 32.6
    },
    {
      "t": 890.0,
      "a": 34.4
    },
    {
      "t": 895.0,
      "a": 35.6
    },
    {
      "t": 900.0,
      "a": 34.8
    },
    {
      "t": 905.0,
      "a": 32.6
    },
    {
      "t": 910.0,
      "a": 30.0
    },
    {
      "t": 915.0,
      "a": 27.6
    },
    {
      "t": 920.0,
      "a": 25.2
    },
    {
      "t": 925.0,
      "a": 22.6
    },
    {
      "t": 930.0,
      "a": 21.8
    },
    {
      "t": 935.0,
      "a": 24.8
    },
    {
      "t": 940.0,
      "a": 28.4
    },
    {
      "t": 945.0,
      "a": 30.6
    },
    {
      "t": 950.0,
      "a": 32.8
    },
    {
      "t": 955.0,
      "a": 34.4
    },
    {
      "t": 960.0,
      "a": 35.4
    },
    {
      "t": 965.0,
      "a": 34.0
    },
    {
      "t": 970.0,
      "a": 31.8
    },
    {
      "t": 975.0,
      "a": 29.2
    },
    {
      "t": 980.0,
      "a": 26.6
    },
    {
      "t": 985.0,
      "a": 24.0
    },
    {
      "t": 990.0,
      "a": 21.8
    },
    {
      "t": 995.0,
      "a": 22.2
    },
    {
      "t": 1000.0,
      "a": 25.2
    },
    {
      "t": 1005.0,
      "a": 28.6
    },
    {
      "t": 1010.0,
      "a": 30.6
    },
    {
      "t": 1015.0,
      "a": 33.0
    },
    {
      "t": 1020.0,
      "a": 34.8
    },
    {
      "t": 1025.0,
      "a": 34.8
    },
    {
      "t": 1030.0,
      "a": 32.8
    },
    {
      "t": 1035.0,
      "a": 30.6
    },
    {
      "t": 1040.0,
      "a": 28.0
    },
    {
      "t": 1045.0,
      "a": 25.6
    },
    {
      "t": 1050.0,
      "a": 22.8
    },
    {
      "t": 1055.0,
      "a": 21.0
    },
    {
      "t": 1060.0,
      "a": 22.8
    },
    {
      "t": 1065.0,
      "a": 26.4
    },
    {
      "t": 1070.0,
      "a": 29.2
    },
    {
      "t": 1075.0,
      "a": 31.4
    },
    {
      "t": 1080.0,
      "a": 33.4
    },
    {
      "t": 1085.0,
      "a": 34.4
    },
    {
      "t": 1090.0,
      "a": 33.6
    },
    {
      "t": 1095.0,
      "a": 31.4
    },
    {
      "t": 1100.0,
      "a": 28.8
    },
    {
      "t": 1105.0,
      "a": 26.2
    },
    {
      "t": 1110.0,
      "a": 23.6
    },
    {
      "t": 1115.0,
      "a": 21.2
    },
    {
      "t": 1120.0,
      "a": 21.0
    },
    {
      "t": 1125.0,
      "a": 24.0
    },
    {
      "t": 1130.0,
      "a": 27.4
    },
    {
      "t": 1135.0,
      "a": 29.6
    },
    {
      "t": 1140.0,
      "a": 31.8
    },
    {
      "t": 1145.0,
      "a": 33.8
    },
    {
      "t": 1150.0,
      "a": 34.0
    },
    {
      "t": 1155.0,
      "a": 32.6
    },
    {
      "t": 1160.0,
      "a": 30.4
    },
    {
      "t": 1165.0,
      "a": 27.8
    },
    {
      "t": 1170.0,
      "a": 25.4
    },
    {
      "t": 1175.0,
      "a": 22.8
    },
    {
      "t": 1180.0,
      "a": 20.4
    },
    {
      "t": 1185.0,
      "a": 21.4
    },
    {
      "t": 1190.0,
      "a": 24.8
    },
    {
      "t": 1195.0,
      "a": 28.0
    },
    {
      "t": 1200.0,
      "a": 30.2
    },
    {
      "t": 1205.0,
      "a": 32.4
    },
    {
      "t": 1210.0,
      "a": 33.6
    },
    {
      "t": 1215.0,
      "a": 33.2
    },
    {
      "t": 1220.0,
      "a": 31.0
    },
    {
      "t": 1225.0,
      "a": 28.4
    },
    {
      "t": 1230.0,
      "a": 25.8
    },
    {
      "t": 1235.0,
      "a": 23.4
    },
    {
      "t": 1240.0,
      "a": 20.6
    },
    {
      "t": 1245.0,
      "a": 20.4
    },
    {
      "t": 1250.0,
      "a": 23.6
    },
    {
      "t": 1255.0,
      "a": 27.0
    },
    {
      "t": 1260.0,
      "a": 29.4
    },
    {
      "t": 1265.0,
      "a": 31.6
    },
    {
      "t": 1270.0,
      "a": 33.0
    },
    {
      "t": 1275.0,
      "a": 33.4
    },
    {
      "t": 1280.0,
      "a": 31.6
    },
    {
      "t": 1285.0,
      "a": 29.2
    },
    {
      "t": 1290.0,
      "a": 26.6
    },
    {
      "t": 1295.0,
      "a": 24.0
    },
    {
      "t": 1300.0,
      "a": 21.4
    },
    {
      "t": 1305.0,
      "a": 19.6
    },
    {
      "t": 1310.0,
      "a": 21.4
    },
    {
      "t": 1315.0,
      "a": 25.0
    },
    {
      "t": 1320.0,
      "a": 27.6
    },
    {
      "t": 1325.0,
      "a": 29.8
    },
    {
      "t": 1330.0,
      "a": 32.0
    },
    {
      "t": 1335.0,
      "a": 33.2
    },
    {
      "t": 1340.0,
      "a": 32.4
    },
    {
      "t": 1345.0,
      "a": 30.2
    },
    {
      "t": 1350.0,
      "a": 27.6
    },
    {
      "t": 1355.0,
      "a": 25.4
    },
    {
      "t": 1360.0,
      "a": 22.8
    },
    {
      "t": 1365.0,
      "a": 20.2
    },
    {
      "t": 1370.0,
      "a": 19.6
    },
    {
      "t": 1375.0,
      "a": 22.6
    },
    {
      "t": 1380.0,
      "a": 26.2
    },
    {
      "t": 1385.0,
      "a": 28.6
    },
    {
      "t": 1390.0,
      "a": 31.0
    },
    {
      "t": 1395.0,
      "a": 32.6
    },
    {
      "t": 1400.0,
      "a": 32.8
    },
    {
      "t": 1405.0,
      "a": 31.0
    },
    {
      "t": 1410.0,
      "a": 28.6
    },
    {
      "t": 1415.0,
      "a": 26.2
    },
    {
      "t": 1420.0,
      "a": 23.6
    },
    {
      "t": 1425.0,
      "a": 20.8
    },
    {
      "t": 1430.0,
      "a": 19.2
    },
    {
      "t": 1435.0,
      "a": 20.8
    },
    {
      "t": 1440.0,
      "a": 24.4
    },
    {
      "t": 1445.0,
      "a": 27.6
    },
    {
      "t": 1450.0,
      "a": 29.6
    },
    {
      "t": 1455.0,
      "a": 31.6
    },
    {
      "t": 1460.0,
      "a": 32.6
    },
    {
      "t": 1465.0,
      "a": 31.8
    },
    {
      "t": 1470.0,
      "a": 29.6
    },
    {
      "t": 1475.0,
      "a": 26.8
    },
    {
      "t": 1480.0,
      "a": 24.4
    },
    {
      "t": 1485.0,
      "a": 22.2
    },
    {
      "t": 1490.0,
      "a": 19.6
    },
    {
      "t": 1495.0,
      "a": 19.0
    },
    {
      "t": 1500.0,
      "a": 21.8
    },
    {
      "t": 1505.0,
      "a": 25.4
    },
    {
      "t": 1510.0,
      "a": 27.8
    },
    {
      "t": 1515.0,
      "a": 30.0
    },
    {
      "t": 1520.0,
      "a": 31.8
    },
    {
      "t": 1525.0,
      "a": 32.2
    },
    {
      "t": 1530.0,
      "a": 30.6
    },
    {
      "t": 1535.0,
      "a": 28.6
    },
    {
      "t": 1540.0,
      "a": 25.8
    },
    {
      "t": 1545.0,
      "a": 23.2
    },
    {
      "t": 1550.0,
      "a": 21.0
    },
    {
      "t": 1555.0,
      "a": 18.6
    },
    {
      "t": 1560.0,
      "a": 19.6
    },
    {
      "t": 1565.0,
      "a": 23.0
    },
    {
      "t": 1570.0,
      "a": 26.0
    },
    {
      "t": 1575.0,
      "a": 28.2
    },
    {
      "t": 1580.0,
      "a": 30.4
    },
    {
      "t": 1585.0,
      "a": 31.8
    },
    {
      "t": 1590.0,
      "a": 31.6
    },
    {
      "t": 1595.0,
      "a": 29.8
    },
    {
      "t": 1600.0,
      "a": 27.4
    },
    {
      "t": 1605.0,
      "a": 24.8
    },
    {
      "t": 1610.0,
      "a": 22.4
    },
    {
      "t": 1615.0,
      "a": 20.0
    },
    {
      "t": 1620.0,
      "a": 18.2
    },
    {
      "t": 1625.0,
      "a": 20.2
    },
    {
      "t": 1630.0,
      "a": 23.8
    },
    {
      "t": 1635.0,
      "a": 26.8
    },
    {
      "t": 1640.0,
      "a": 29.0
    },
    {
      "t": 1645.0,
      "a": 30.8
    },
    {
      "t": 1650.0,
      "a": 31.8
    },
    {
      "t": 1655.0,
      "a": 31.2
    },
    {
      "t": 1660.0,
      "a": 29.0
    },
    {
      "t": 1665.0,
      "a": 26.8
    },
    {
      "t": 1670.0,
      "a": 24.2
    },
    {
      "t": 1675.0,
      "a": 21.8
    },
    {
      "t": 1680.0,
      "a": 19.2
    },
    {
      "t": 1685.0,
      "a": 18.2
    },
    {
      "t": 1690.0,
      "a": 20.8
    },
    {
      "t": 1695.0,
      "a": 24.4
    },
    {
      "t": 1700.0,
      "a": 26.6
    },
    {
      "t": 1705.0,
      "a": 29.0
    },
    {
      "t": 1710.0,
      "a": 30.6
    },
    {
      "t": 1715.0,
      "a": 31.6
    },
    {
      "t": 1720.0,
      "a": 30.6
    },
    {
      "t": 1725.0,
      "a": 28.2
    },
    {
      "t": 1730.0,
      "a": 25.8
    },
    {
      "t": 1735.0,
      "a": 23.2
    },
    {
      "t": 1740.0,
      "a": 20.8
    },
    {
      "t": 1745.0,
      "a": 18.2
    },
    {
      "t": 1750.0,
      "a": 18.2
    },
    {
      "t": 1755.0,
      "a": 21.4
    },
    {
      "t": 1760.0,
      "a": 25.0
    },
    {
      "t": 1765.0,
      "a": 27.2
    },
    {
      "t": 1770.0,
      "a": 29.2
    },
    {
      "t": 1775.0,
      "a": 30.8
    },
    {
      "t": 1780.0,
      "a": 31.0
    },
    {
      "t": 1785.0,
      "a": 29.4
    },
    {
      "t": 1790.0,
      "a": 27.4
    },
    {
      "t": 1795.0,
      "a": 24.8
    },
    {
      "t": 1800.0,
      "a": 22.2
    },
    {
      "t": 1805.0,
      "a": 19.6
    },
    {
      "t": 1810.0,
      "a": 17.4
    },
    {
      "t": 1815.0,
      "a": 18.8
    },
    {
      "t": 1820.0,
      "a": 22.2
    },
    {
      "t": 1825.0,
      "a": 25.6
    },
    {
      "t": 1830.0,
      "a": 27.6
    },
    {
      "t": 1835.0,
      "a": 29.4
    },
    {
      "t": 1840.0,
      "a": 30.8
    },
    {
      "t": 1845.0,
      "a": 30.2
    },
    {
      "t": 1850.0,
      "a": 28.4
    },
    {
      "t": 1855.0,
      "a": 26.0
    },
    {
      "t": 1860.0,
      "a": 23.2
    },
    {
      "t": 1865.0,
      "a": 20.8
    },
    {
      "t": 1870.0,
      "a": 18.4
    },
    {
      "t": 1875.0,
      "a": 17.2
    },
    {
      "t": 1880.0,
      "a": 19.8
    },
    {
      "t": 1885.0,
      "a": 23.4
    },
    {
      "t": 1890.0,
      "a": 26.0
    },
    {
      "t": 1895.0,
      "a": 28.0
    },
    {
      "t": 1900.0,
      "a": 29.8
    },
    {
      "t": 1905.0,
      "a": 30.6
    },
    {
      "t": 1910.0,
      "a": 29.6
    },
    {
      "t": 1915.0,
      "a": 27.2
    },
    {
      "t": 1920.0,
      "a": 24.6
    },
    {
      "t": 1925.0,
      "a": 22.4
    },
    {
      "t": 1930.0,
      "a": 19.6
    },
    {
      "t": 1935.0,
      "a": 17.0
    },
    {
      "t": 1940.0,
      "a": 17.4
    },
    {
      "t": 1945.0,
      "a": 20.4
    },
    {
      "t": 1950.0,
      "a": 24.0
    },
    {
      "t": 1955.0,
      "a": 26.2
    },
    {
      "t": 1960.0,
      "a": 28.4
    },
    {
      "t": 1965.0,
      "a": 30.0
    },
    {
      "t": 1970.0,
      "a": 30.0
    },
    {
      "t": 1975.0,
      "a": 28.0
    },
    {
      "t": 1980.0,
      "a": 25.8
    },
    {
      "t": 1985.0,
      "a": 23.2
    },
    {
      "t": 1990.0,
      "a": 20.8
    },
    {
      "t": 1995.0,
      "a": 18.2
    },
    {
      "t": 2000.0,
      "a": 16.4
    },
    {
      "t": 2005.0,
      "a": 17.6
    },
    {
      "t": 2010.0,
      "a": 20.4
    },
    {
      "t": 2015.0,
      "a": 23.0
    },
    {
      "t": 2020.0,
      "a": 24.6
    },
    {
      "t": 2025.0,
      "a": 26.8
    },
    {
      "t": 2030.0,
      "a": 28.4
    },
    {
      "t": 2035.0,
      "a": 30.0
    },
    {
      "t": 2040.0,
      "a": 29.4
    },
    {
      "t": 2045.0,
      "a": 27.4
    },
    {
      "t": 2050.0,
      "a": 25.2
    },
    {
      "t": 2055.0,
      "a": 22.8
    },
    {
      "t": 2060.0,
      "a": 20.4
    },
    {
      "t": 2065.0,
      "a": 17.8
    },
    {
      "t": 2070.0,
      "a": 16.2
    },
    {
      "t": 2075.0,
      "a": 18.0
    },
    {
      "t": 2080.0,
      "a": 21.4
    },
    {
      "t": 2085.0,
      "a": 24.2
    },
    {
      "t": 2090.0,
      "a": 26.2
    },
    {
      "t": 2095.0,
      "a": 28.2
    },
    {
      "t": 2100.0,
      "a": 29.6
    },
    {
      "t": 2105.0,
      "a": 29.4
    },
    {
      "t": 2110.0,
      "a": 27.2
    },
    {
      "t": 2115.0,
      "a": 25.0
    },
    {
      "t": 2120.0,
      "a": 22.6
    },
    {
      "t": 2125.0,
      "a": 20.0
    },
    {
      "t": 2130.0,
      "a": 17.2
    },
    {
      "t": 2135.0,
      "a": 16.0
    },
    {
      "t": 2140.0,
      "a": 18.4
    },
    {
      "t": 2145.0,
      "a": 22.0
    },
    {
      "t": 2150.0,
      "a": 24.4
    },
    {
      "t": 2155.0,
      "a": 26.6
    },
    {
      "t": 2160.0,
      "a": 28.4
    },
    {
      "t": 2165.0,
      "a": 29.6
    },
    {
      "t": 2170.0,
      "a": 28.6
    },
    {
      "t": 2175.0,
      "a": 26.4
    },
    {
      "t": 2180.0,
      "a": 24.0
    },
    {
      "t": 2185.0,
      "a": 21.4
    },
    {
      "t": 2190.0,
      "a": 18.8
    },
    {
      "t": 2195.0,
      "a": 16.4
    },
    {
      "t": 2200.0,
      "a": 16.2
    },
    {
      "t": 2205.0,
      "a": 19.2
    },
    {
      "t": 2210.0,
      "a": 22.6
    },
    {
      "t": 2215.0,
      "a": 26.4
    },
    {
      "t": 2220.0,
      "a": 28.0
    },
    {
      "t": 2225.0,
      "a": 29.2
    },
    {
      "t": 2230.0,
      "a": 28.8
    },
    {
      "t": 2235.0,
      "a": 26.6
    },
    {
      "t": 2240.0,
      "a": 24.4
    },
    {
      "t": 2245.0,
      "a": 22.0
    },
    {
      "t": 2250.0,
      "a": 19.4
    },
    {
      "t": 2255.0,
      "a": 17.0
    },
    {
      "t": 2260.0,
      "a": 15.4
    },
    {
      "t": 2265.0,
      "a": 17.6
    },
    {
      "t": 2270.0,
      "a": 21.2
    },
    {
      "t": 2275.0,
      "a": 23.6
    },
    {
      "t": 2280.0,
      "a": 25.8
    },
    {
      "t": 2285.0,
      "a": 27.8
    },
    {
      "t": 2307.0,
      "a": 28.8
    },
    {
      "t": 2312.0,
      "a": 27.8
    },
    {
      "t": 2317.0,
      "a": 25.8
    },
    {
      "t": 2322.0,
      "a": 23.6
    },
    {
      "t": 2327.0,
      "a": 21.0
    },
    {
      "t": 2332.0,
      "a": 18.6
    },
    {
      "t": 2337.0,
      "a": 16.0
    },
    {
      "t": 2342.0,
      "a": 15.4
    },
    {
      "t": 2347.0,
      "a": 18.2
    },
    {
      "t": 2352.0,
      "a": 21.6
    },
    {
      "t": 2357.0,
      "a": 23.8
    },
    {
      "t": 2362.0,
      "a": 26.2
    },
    {
      "t": 2367.0,
      "a": 28.2
    },
    {
      "t": 2372.0,
      "a": 28.8
    },
    {
      "t": 2377.0,
      "a": 27.0
    },
    {
      "t": 2382.0,
      "a": 24.8
    },
    {
      "t": 2387.0,
      "a": 22.2
    },
    {
      "t": 2392.0,
      "a": 19.8
    },
    {
      "t": 2397.0,
      "a": 17.2
    },
    {
      "t": 2402.0,
      "a": 15.2
    },
    {
      "t": 2407.0,
      "a": 16.6
    },
    {
      "t": 2412.0,
      "a": 20.0
    },
    {
      "t": 2417.0,
      "a": 23.0
    },
    {
      "t": 2422.0,
      "a": 25.0
    },
    {
      "t": 2427.0,
      "a": 27.0
    },
    {
      "t": 2432.0,
      "a": 28.4
    },
    {
      "t": 2437.0,
      "a": 28.2
    },
    {
      "t": 2442.0,
      "a": 26.2
    },
    {
      "t": 2447.0,
      "a": 23.6
    },
    {
      "t": 2452.0,
      "a": 21.0
    },
    {
      "t": 2457.0,
      "a": 18.6
    },
    {
      "t": 2462.0,
      "a": 16.2
    },
    {
      "t": 2467.0,
      "a": 15.0
    },
    {
      "t": 2472.0,
      "a": 17.6
    },
    {
      "t": 2477.0,
      "a": 21.4
    },
    {
      "t": 2482.0,
      "a": 24.6
    },
    {
      "t": 2487.0,
      "a": 26.6
    },
    {
      "t": 2492.0,
      "a": 28.2
    },
    {
      "t": 2497.0,
      "a": 28.6
    },
    {
      "t": 2502.0,
      "a": 26.2
    },
    {
      "t": 2507.0,
      "a": 24.2
    },
    {
      "t": 2512.0,
      "a": 21.6
    },
    {
      "t": 2517.0,
      "a": 19.0
    },
    {
      "t": 2522.0,
      "a": 16.4
    },
    {
      "t": 2527.0,
      "a": 15.0
    },
    {
      "t": 2532.0,
      "a": 16.6
    },
    {
      "t": 2537.0,
      "a": 20.2
    },
    {
      "t": 2542.0,
      "a": 23.0
    },
    {
      "t": 2547.0,
      "a": 25.4
    },
    {
      "t": 2552.0,
      "a": 27.2
    },
    {
      "t": 2557.0,
      "a": 28.4
    },
    {
      "t": 2562.0,
      "a": 27.4
    },
    {
      "t": 2567.0,
      "a": 25.2
    },
    {
      "t": 2572.0,
      "a": 22.8
    },
    {
      "t": 2577.0,
      "a": 20.2
    },
    {
      "t": 2582.0,
      "a": 17.8
    },
    {
      "t": 2587.0,
      "a": 15.2
    },
    {
      "t": 2592.0,
      "a": 15.4
    },
    {
      "t": 2597.0,
      "a": 18.4
    },
    {
      "t": 2602.0,
      "a": 22.0
    },
    {
      "t": 2607.0,
      "a": 24.0
    },
    {
      "t": 2612.0,
      "a": 26.4
    },
    {
      "t": 2617.0,
      "a": 28.0
    },
    {
      "t": 2622.0,
      "a": 28.2
    },
    {
      "t": 2627.0,
      "a": 25.6
    },
    {
      "t": 2632.0,
      "a": 23.4
    },
    {
      "t": 2637.0,
      "a": 20.8
    },
    {
      "t": 2642.0,
      "a": 18.2
    },
    {
      "t": 2647.0,
      "a": 15.6
    },
    {
      "t": 2652.0,
      "a": 14.6
    },
    {
      "t": 2657.0,
      "a": 17.2
    },
    {
      "t": 2662.0,
      "a": 21.0
    },
    {
      "t": 2667.0,
      "a": 23.8
    },
    {
      "t": 2672.0,
      "a": 25.8
    },
    {
      "t": 2677.0,
      "a": 27.4
    },
    {
      "t": 2682.0,
      "a": 28.2
    },
    {
      "t": 2687.0,
      "a": 26.6
    },
    {
      "t": 2692.0,
      "a": 24.2
    },
    {
      "t": 2697.0,
      "a": 21.4
    },
    {
      "t": 2702.0,
      "a": 19.2
    },
    {
      "t": 2707.0,
      "a": 16.4
    },
    {
      "t": 2712.0,
      "a": 14.6
    },
    {
      "t": 2717.0,
      "a": 14.2
    },
    {
      "t": 2722.0,
      "a": 13.8
    },
    {
      "t": 2727.0,
      "a": 12.8
    },
    {
      "t": 2732.0,
      "a": 12.0
    },
    {
      "t": 2737.0,
      "a": 10.4
    },
    {
      "t": 2742.0,
      "a": 9.0
    },
    {
      "t": 2747.0,
      "a": 8.0
    },
    {
      "t": 2752.0,
      "a": 7.4
    },
    {
      "t": 2757.0,
      "a": 7.0
    },
    {
      "t": 2762.0,
      "a": 6.6
    },
    {
      "t": 2767.0,
      "a": 6.0
    },
    {
      "t": 2772.0,
      "a": 6.0
    },
    {
      "t": 2777.0,
      "a": 5.8
    },
    {
      "t": 2782.0,
      "a": 5.6
    },
    {
      "t": 2787.0,
      "a": 5.2
    },
    {
      "t": 2792.0,
      "a": 4.8
    },
    {
      "t": 2797.0,
      "a": 4.4
    },
    {
      "t": 2802.0,
      "a": 4.6
    },
    {
      "t": 2807.0,
      "a": 4.8
    },
    {
      "t": 2812.0,
      "a": 4.6
    },
    {
      "t": 2817.0,
      "a": 4.6
    },
    {
      "t": 2822.0,
      "a": 4.8
    },
    {
      "t": 2827.0,
      "a": 4.6
    },
    {
      "t": 2832.0,
      "a": 4.6
    },
    {
      "t": 2837.0,
      "a": 4.6
    },
    {
      "t": 2842.0,
      "a": 4.2
    },
    {
      "t": 2847.0,
      "a": 4.4
    },
    {
      "t": 2852.0,
      "a": 4.2
    },
    {
      "t": 2857.0,
      "a": 4.2
    },
    {
      "t": 2862.0,
      "a": 4.2
    },
    {
      "t": 2867.0,
      "a": 4.2
    },
    {
      "t": 2872.0,
      "a": 4.2
    },
    {
      "t": 2877.0,
      "a": 4.0
    },
    {
      "t": 2882.0,
      "a": 4.2
    },
    {
      "t": 2887.0,
      "a": 4.2
    },
    {
      "t": 2892.0,
      "a": 4.0
    },
    {
      "t": 2897.0,
      "a": 3.8
    },
    {
      "t": 2902.0,
      "a": 3.8
    },
    {
      "t": 2907.0,
      "a": 4.0
    },
    {
      "t": 2912.0,
      "a": 4.0
    },
    {
      "t": 2917.0,
      "a": 4.0
    },
    {
      "t": 2922.0,
      "a": 4.0
    },
    {
      "t": 2927.0,
      "a": 4.0
    },
    {
      "t": 2932.0,
      "a": 4.0
    },
    {
      "t": 2937.0,
      "a": 3.8
    },
    {
      "t": 2942.0,
      "a": 3.8
    },
    {
      "t": 2947.0,
      "a": 4.0
    },
    {
      "t": 2952.0,
      "a": 4.0
    },
    {
      "t": 2957.0,
      "a": 4.0
    },
    {
      "t": 2962.0,
      "a": 4.0
    },
    {
      "t": 2967.0,
      "a": 4.0
    },
    {
      "t": 2972.0,
      "a": 4.2
    },
    {
      "t": 2977.0,
      "a": 4.0
    },
    {
      "t": 2982.0,
      "a": 4.0
    },
    {
      "t": 2987.0,
      "a": 4.2
    },
    {
      "t": 2992.0,
      "a": 4.2
    },
    {
      "t": 2997.0,
      "a": 4.4
    },
    {
      "t": 3002.0,
      "a": 4.8
    },
    {
      "t": 3007.0,
      "a": 4.8
    },
    {
      "t": 3012.0,
      "a": 4.6
    },
    {
      "t": 3017.0,
      "a": 4.8
    },
    {
      "t": 3022.0,
      "a": 4.8
    },
    {
      "t": 3027.0,
      "a": 5.2
    },
    {
      "t": 3032.0,
      "a": 5.4
    },
    {
      "t": 3037.0,
      "a": 5.4
    },
    {
      "t": 3042.0,
      "a": 5.6
    },
    {
      "t": 3047.0,
      "a": 5.8
    },
    {
      "t": 3052.0,
      "a": 6.0
    },
    {
      "t": 3057.0,
      "a": 6.4
    },
    {
      "t": 3062.0,
      "a": 6.8
    },
    {
      "t": 3067.0,
      "a": 6.8
    },
    {
      "t": 3072.0,
      "a": 6.6
    },
    {
      "t": 3077.0,
      "a": 6.2
    },
    {
      "t": 3082.0,
      "a": 6.0
    },
    {
      "t": 3087.0,
      "a": 6.0
    },
    {
      "t": 3092.0,
      "a": 6.6
    },
    {
      "t": 3097.0,
      "a": 6.2
    },
    {
      "t": 3102.0,
      "a": 6.6
    },
    {
      "t": 3107.0,
      "a": 6.6
    },
    {
      "t": 3112.0,
      "a": 6.8
    },
    {
      "t": 3117.0,
      "a": 6.8
    },
    {
      "t": 3122.0,
      "a": 6.8
    },
    {
      "t": 3127.0,
      "a": 7.0
    },
    {
      "t": 3132.0,
      "a": 7.0
    },
    {
      "t": 3137.0,
      "a": 6.8
    },
    {
      "t": 3142.0,
      "a": 6.8
    },
    {
      "t": 3147.0,
      "a": 6.8
    },
    {
      "t": 3152.0,
      "a": 6.6
    },
    {
      "t": 3157.0,
      "a": 6.4
    },
    {
      "t": 3162.0,
      "a": 6.2
    },
    {
      "t": 3167.0,
      "a": 5.8
    },
    {
      "t": 3172.0,
      "a": 5.0
    },
    {
      "t": 3177.0,
      "a": 4.4
    },
    {
      "t": 3182.0,
      "a": 4.2
    },
    {
      "t": 3187.0,
      "a": 4.2
    },
    {
      "t": 3192.0,
      "a": 4.0
    },
    {
      "t": 3197.0,
      "a": 4.0
    },
    {
      "t": 3202.0,
      "a": 4.4
    },
    {
      "t": 3207.0,
      "a": 4.0
    },
    {
      "t": 3212.0,
      "a": 3.8
    },
    {
      "t": 3217.0,
      "a": 3.8
    },
    {
      "t": 3222.0,
      "a": 3.4
    },
    {
      "t": 3227.0,
      "a": 4.0
    },
    {
      "t": 3232.0,
      "a": 4.0
    }
  ],
  "valleys": [
    {
      "t": 505.0,
      "a": 18.8
    },
    {
      "t": 609.0,
      "a": 23.6
    },
    {
      "t": 673.0,
      "a": 23.4
    },
    {
      "t": 736.0,
      "a": 22.8
    },
    {
      "t": 799.0,
      "a": 22.4
    },
    {
      "t": 864.0,
      "a": 22.0
    },
    {
      "t": 928.0,
      "a": 21.6
    },
    {
      "t": 992.0,
      "a": 21.4
    },
    {
      "t": 1055.0,
      "a": 21.0
    },
    {
      "t": 1117.0,
      "a": 20.6
    },
    {
      "t": 1181.0,
      "a": 20.2
    },
    {
      "t": 1243.0,
      "a": 20.0
    },
    {
      "t": 1305.0,
      "a": 19.6
    },
    {
      "t": 1368.0,
      "a": 19.4
    },
    {
      "t": 1430.0,
      "a": 19.2
    },
    {
      "t": 1493.0,
      "a": 18.8
    },
    {
      "t": 1556.0,
      "a": 18.4
    },
    {
      "t": 1619.0,
      "a": 18.2
    },
    {
      "t": 1684.0,
      "a": 18.0
    },
    {
      "t": 1748.0,
      "a": 17.6
    },
    {
      "t": 1810.0,
      "a": 17.4
    },
    {
      "t": 1873.0,
      "a": 17.2
    },
    {
      "t": 1937.0,
      "a": 16.6
    },
    {
      "t": 2000.0,
      "a": 16.4
    },
    {
      "t": 2070.0,
      "a": 16.2
    },
    {
      "t": 2134.0,
      "a": 16.0
    },
    {
      "t": 2197.0,
      "a": 15.8
    },
    {
      "t": 2260.0,
      "a": 15.4
    },
    {
      "t": 2340.0,
      "a": 15.2
    },
    {
      "t": 2403.0,
      "a": 15.0
    },
    {
      "t": 2466.0,
      "a": 15.0
    },
    {
      "t": 2526.0,
      "a": 15.0
    },
    {
      "t": 2589.0,
      "a": 14.8
    },
    {
      "t": 2651.0,
      "a": 14.4
    },
    {
      "t": 2718.0,
      "a": 14.0
    }
  ],
  "sawtooth_start_t": 492.0,
  "sawtooth_end_t": 2768.0,
  "workout_date": "31 Jan 2026",
  "hill": {
    "id": "trappen-citadel-diest",
    "name": "Trappen Citadel Diest"
  },
  "summary": {
    "num_reps": 34,
    "rep_total_elevation": 466.4,
    "avg_elevation": 13.7,
    "avg_rep_time": 65.0,
    "strava_elevation_gain": 436.0,
    "workout_duration": 3234,
    "workout_distance": 6812.0
  }
}